inaudible/__init__.py
inaudible/scikits_talkbox.py
inaudible/speaking_clock_detection.py
speaking_clock_detection-1.1.2.data/scripts/speaking_clock_detection
speaking_clock_detection-1.1.2.dist-info/licenses/LICENSE
speaking_clock_detection-1.1.2.dist-info/METADATA
speaking_clock_detection-1.1.2.dist-info/WHEEL
speaking_clock_detection-1.1.2.dist-info/top_level.txt
speaking_clock_detection-1.1.2.dist-info/RECORD
