Metadata-Version: 2.4
Name: speaking-clock-detection
Version: 1.1.2
Author-email: David Doukhan <ddoukhan@ina.fr>, Cournapeau David <cournape@gmail.com>, Valentin Pelloin <vpelloin@ina.fr>
Project-URL: Homepage, https://github.com/ina-foss/speaking-clock-detection
Requires-Python: >=3.6
License-File: LICENSE
Requires-Dist: soundfile
Requires-Dist: scipy
Requires-Dist: numpy
Dynamic: license-file
